mlviz/__init__.py
mlviz/timeseries/__init__.py
mlviz/timeseries/visualizationhelpers.py
mlviz/utilities/__init__.py
mlviz/utilities/commonhelpers.py
mlviz/utilities/graphichelpers.py
mlviz/utilities/imagehelpers.py
mlviz-0.1.4.dist-info/LICENSE
mlviz-0.1.4.dist-info/METADATA
mlviz-0.1.4.dist-info/WHEEL
mlviz-0.1.4.dist-info/top_level.txt
mlviz-0.1.4.dist-info/RECORD
